iuextract/__init__.py
iuextract/__main__.py
iuextract/cli.py
iuextract/data.py
iuextract/extract.py
iuextract/gold.py
iuextract/iu_utils.py
iuextract/transition_signals.txt
IUExtract-1.0.9.dist-info/LICENSE
IUExtract-1.0.9.dist-info/METADATA
IUExtract-1.0.9.dist-info/WHEEL
IUExtract-1.0.9.dist-info/entry_points.txt
IUExtract-1.0.9.dist-info/top_level.txt
IUExtract-1.0.9.dist-info/RECORD
