Metadata-Version: 2.1
Name: IUExtract
Version: 1.0.9
Summary: Rule-based Idea Unit segmentation algorithm for the English language.
Home-page: https://github.com/TT-CL/iuextract
Author: Gecchele Marcello
Author-email: Marcello Gecchele <linked.uno@pm.me>
License: The Clear BSD License
Project-URL: Homepage, https://tt-cl.github.io/iu-resources/
Project-URL: Documentation, https://github.com/TT-CL/iuextract
Project-URL: Repository, https://github.com/TT-CL/iuextract.git
Project-URL: Issues, https://github.com/TT-CL/iuextract/issues
Keywords: Idea Unit,textual segmentation,segmentation,linguistics
Classifier: Programming Language :: Python :: 3
Classifier: License :: OSI Approved :: MIT License
Classifier: Operating System :: OS Independent
Requires-Python: >=3.8
License-File: LICENSE
Requires-Dist: spacy>=3.0.0
